Andreani_QA_Debugger/Debugger.py
Andreani_QA_Debugger/__init__.py
Andreani_QA_Debugger-0.0.8.dist-info/METADATA
Andreani_QA_Debugger-0.0.8.dist-info/WHEEL
Andreani_QA_Debugger-0.0.8.dist-info/top_level.txt
Andreani_QA_Debugger-0.0.8.dist-info/RECORD
