Metadata-Version: 2.1
Name: Andreani-QA-Debugger
Version: 0.0.8
Summary: Debugger para ejecución de casos automatizados
Home-page: UNKNOWN
Author: AndreaniTesting
Author-email: user_appglatest@andreani.com
License: MIT
Platform: UNKNOWN
Requires-Dist: pywebview
Requires-Dist: python-docx
